sshkeyring/__init__.py
sshkeyring/paramiko_supplement.py
sshkeyring/sshkeyinfo.py
sshkeyring/sshkeyring.py
sshkeyring/sshkeyutil.py
sshkeyring-0.0.6.dist-info/LICENSE
sshkeyring-0.0.6.dist-info/METADATA
sshkeyring-0.0.6.dist-info/WHEEL
sshkeyring-0.0.6.dist-info/top_level.txt
sshkeyring-0.0.6.dist-info/RECORD
