Metadata-Version: 2.2
Name: sshkeyring
Version: 0.0.6
Summary: Utilities to manage SSH key in key files and ssh-agent
Home-page: https://github.com/nanigashi-uji/sshkeyring.git
Author: Nanigashi Uji
Author-email: 53845049+nanigashi-uji@users.noreply.github.com
License: BSD-3-Clause
Keywords: ssh-keyfile utility ssh-agent utility
Classifier: Development Status :: 4 - Beta
Classifier: License :: OSI Approved :: BSD License
Classifier: Programming Language :: Python
Classifier: Programming Language :: Python :: 3
Classifier: Topic :: Security :: Cryptography
Classifier: Topic :: Software Development :: Libraries :: Python Modules
Classifier: Topic :: System :: Software Distribution
Classifier: Topic :: Utilities
License-File: LICENSE
Requires-Dist: cryptography
Requires-Dist: paramiko
Requires-Dist: pkgstruct
Requires-Dist: PyNaCl
Dynamic: author
Dynamic: author-email
Dynamic: classifier
Dynamic: description
Dynamic: home-page
Dynamic: keywords
Dynamic: license
Dynamic: requires-dist
Dynamic: summary
